utils/__init__.py
utils/decorators.py
utils/fields.py
utils/frontmatter.py
utils/logging.py
utils/mixins.py
utils/pipeline_compilers.py
utils/pipeline_compressors.py
utils/raven.py
utils/shorturl.py
utils/signing.py
utils/storage.py
utils/urls.py
utils/validators.py
utils/management/__init__.py
utils/management/commands/__init__.py
utils/management/commands/clean_staticfilesjson.py
utils/middlewares/__init__.py
utils/middlewares/latency.py
utils/sass_functions/__init__.py
utils/sass_functions/svg_to_data_uri.py
utils/templatetags/__init__.py
utils/templatetags/absolute_url.py
utils/templatetags/jsonify.py
utils/templatetags/md.py
utils/tests/__init__.py
utils/tests/test_absolute_url.py
utils/tests/test_decorators.py
utils/tests/test_emaillistvalidator.py
utils/tests/test_frontmatter.py
utils/tests/test_jsonify.py
utils/tests/test_jsonprettyfield.py
utils/tests/test_latency_middleware.py
utils/tests/test_markdown.py
utils/tests/test_pipeline.py
utils/tests/test_raven.py
utils/tests/test_signing.py
utils/tests/test_storage.py
utils/tests/test_templatetags_markdown.py
utils/tests/test_yamlprettyfield.py
bulv1ne_django_utils-0.3.0.dist-info/LICENSE
bulv1ne_django_utils-0.3.0.dist-info/METADATA
bulv1ne_django_utils-0.3.0.dist-info/WHEEL
bulv1ne_django_utils-0.3.0.dist-info/top_level.txt
bulv1ne_django_utils-0.3.0.dist-info/RECORD
