Metadata-Version: 2.1
Name: bulv1ne-django-utils
Version: 0.3.0
Summary: Django utils for all kinds of situations
Home-page: https://github.com/bulv1ne/django-utils
Author: Niels Lemmens
Author-email: draso.odin@gmail.com
License: MIT
Keywords: django,utils
Platform: UNKNOWN
Classifier: Development Status :: 4 - Beta
Classifier: Environment :: Web Environment
Classifier: Framework :: Django
Classifier: Intended Audience :: Developers
Classifier: License :: OSI Approved :: MIT License
Classifier: Programming Language :: Python
Classifier: Programming Language :: Python :: 3
Classifier: Programming Language :: Python :: 3.7
Classifier: Programming Language :: Python :: 3.8
Classifier: Programming Language :: Python :: 3.9
Classifier: Topic :: Software Development
Classifier: Topic :: Utilities
Requires-Dist: django (>=2.2)
Provides-Extra: all
Requires-Dist: Markdown (<3.4,>=3.0) ; extra == 'all'
Requires-Dist: django-pipeline (<2.1,>=2.0) ; extra == 'all'
Requires-Dist: libsass (<0.21,>=0.20) ; extra == 'all'
Requires-Dist: csscompressor (<1.0,>=0.9) ; extra == 'all'
Requires-Dist: raven (<6.1,>=6.0) ; extra == 'all'
Requires-Dist: boto3 ; extra == 'all'
Requires-Dist: PyYAML (<6,>=5) ; extra == 'all'
Requires-Dist: psycopg2-binary (>=2.7) ; extra == 'all'
Provides-Extra: frontmatter
Requires-Dist: PyYAML (<6,>=5) ; extra == 'frontmatter'
Provides-Extra: json
Requires-Dist: psycopg2-binary (>=2.7) ; extra == 'json'
Provides-Extra: markdown
Requires-Dist: Markdown (<3.4,>=3.0) ; extra == 'markdown'
Provides-Extra: pipeline
Requires-Dist: django-pipeline (<2.1,>=2.0) ; extra == 'pipeline'
Requires-Dist: libsass (<0.21,>=0.20) ; extra == 'pipeline'
Requires-Dist: csscompressor (<1.0,>=0.9) ; extra == 'pipeline'
Provides-Extra: raven
Requires-Dist: raven (<6.1,>=6.0) ; extra == 'raven'
Provides-Extra: s3
Requires-Dist: boto3 ; extra == 's3'
